KcangFuse/__init__.py
KcangFuse/funcFuse.py
KcangFuse-1.0.dist-info/LICENSE.txt
KcangFuse-1.0.dist-info/METADATA
KcangFuse-1.0.dist-info/WHEEL
KcangFuse-1.0.dist-info/top_level.txt
KcangFuse-1.0.dist-info/RECORD
